odoo/addons/web_form_banner/README.rst
odoo/addons/web_form_banner/__init__.py
odoo/addons/web_form_banner/__manifest__.py
odoo/addons/web_form_banner/demo/web_form_banner_rule_demo.xml
odoo/addons/web_form_banner/i18n/it.po
odoo/addons/web_form_banner/i18n/ja.po
odoo/addons/web_form_banner/i18n/web_form_banner.pot
odoo/addons/web_form_banner/models/__init__.py
odoo/addons/web_form_banner/models/ir_model.py
odoo/addons/web_form_banner/models/web_form_banner_rule.py
odoo/addons/web_form_banner/readme/CONTRIBUTORS.md
odoo/addons/web_form_banner/readme/DESCRIPTION.md
odoo/addons/web_form_banner/readme/ROADMAP.md
odoo/addons/web_form_banner/readme/USAGE.md
odoo/addons/web_form_banner/security/ir.model.access.csv
odoo/addons/web_form_banner/static/description/icon.png
odoo/addons/web_form_banner/static/description/index.html
odoo/addons/web_form_banner/static/description/partner_email_rule.png
odoo/addons/web_form_banner/static/description/partner_layout_banner.png
odoo/addons/web_form_banner/static/description/partner_layout_no_banner.png
odoo/addons/web_form_banner/static/description/partner_tag_rule.png
odoo/addons/web_form_banner/static/src/js/web_form_banner.esm.js
odoo/addons/web_form_banner/static/src/scss/web_form_banner.scss
odoo/addons/web_form_banner/tests/__init__.py
odoo/addons/web_form_banner/tests/test_web_form_banner.py
odoo/addons/web_form_banner/views/web_form_banner_rule_views.xml
odoo_addon_web_form_banner-18.0.1.0.1.dist-info/METADATA
odoo_addon_web_form_banner-18.0.1.0.1.dist-info/WHEEL
odoo_addon_web_form_banner-18.0.1.0.1.dist-info/top_level.txt
odoo_addon_web_form_banner-18.0.1.0.1.dist-info/RECORD
